httpie_hmac/__init__.py
httpie_hmac/httpie_hmac.py
httpie_hmac-1.2.0.dist-info/LICENSE
httpie_hmac-1.2.0.dist-info/METADATA
httpie_hmac-1.2.0.dist-info/WHEEL
httpie_hmac-1.2.0.dist-info/entry_points.txt
httpie_hmac-1.2.0.dist-info/top_level.txt
httpie_hmac-1.2.0.dist-info/RECORD
