Metadata-Version: 2.1
Name: httpie-hmac
Version: 1.2.0
Summary: HMAC Auth Plugin for Httpie
Author-email: Martyn Pittuck-Schols <martyn@rustfoo.com>
License: MIT
Project-URL: homepage, https://github.com/martynp/httpie-hmac/
Project-URL: repository, https://github.com/martynp/httpie-hmac.git
Keywords: httpie,auth,hmac,aws4
Classifier: License :: OSI Approved :: MIT License
Classifier: Programming Language :: Python :: 3
Requires-Python: >=3.7
License-File: LICENSE
Requires-Dist: aws-requests-auth
Requires-Dist: httpie
Requires-Dist: requests
